Metadata-Version: 2.1
Name: boxhed-prep
Version: 2.4
Summary: preprocessor for BoXHED2.0
Author: Arash Pakbin
Requires-Python: >=3.8
